sharpshot/__init__.py
sharpshot/analyze_template.html
sharpshot/cli.py
sharpshot/error.py
sharpshot/report.py
sharpshot/run.py
sharpshot/tools.py
sharpshot/core/__init__.py
sharpshot/core/analyze.py
sharpshot/core/config.py
sharpshot/core/constant.py
sharpshot/core/database.py
sharpshot/core/diff_parse.py
sharpshot/core/graph.py
sharpshot/core/java_parse.py
sharpshot/core/mapper_parse.py
sharpshot/core/sql.py
sharpshot-1.0.2.dist-info/LICENSE
sharpshot-1.0.2.dist-info/METADATA
sharpshot-1.0.2.dist-info/WHEEL
sharpshot-1.0.2.dist-info/entry_points.txt
sharpshot-1.0.2.dist-info/top_level.txt
sharpshot-1.0.2.dist-info/RECORD
