Metadata-Version: 2.1
Name: sharpshot
Version: 1.0.2
Summary: Sharpshot will help you tests more easily! Created: Lijiawei. Version 1.0.2
Home-page: https://github.com/openutx
Author: lijiawei
Author-email: jiawei.li2@qq.com
License: Apache License 2.0
Keywords: sharpshot,test,static-code-analysis,tools
Platform: any
Classifier: Development Status :: 5 - Production/Stable
Classifier: Environment :: Console :: Curses
Classifier: Operating System :: MacOS
Classifier: Operating System :: POSIX
Classifier: Operating System :: Microsoft :: Windows
Classifier: Programming Language :: Python :: 3 :: Only
Classifier: Programming Language :: Python :: 3.6
Classifier: Programming Language :: Python :: 3.7
Classifier: Programming Language :: Python :: 3.8
Classifier: Programming Language :: Python :: 3.9
Classifier: Programming Language :: Python :: Implementation :: CPython
License-File: LICENSE
Requires-Dist: javalang==0.13.0
Requires-Dist: unidiff~=0.7.4
Requires-Dist: jinja2
Requires-Dist: requests
